[{"langUid":-4103245208651555003,"name":"0","langLocalChangeSeqNum":0,"langMasterChangeSeqNum":8026,"langLastChangedBy":-955361223},{"langUid":-4103245208651555002,"name":"","langLocalChangeSeqNum":0,"langMasterChangeSeqNum":8027,"langLastChangedBy":-955361223},{"langUid":-4103245208651555001,"name":"Lukhonzo","langLocalChangeSeqNum":0,"langMasterChangeSeqNum":8028,"langLastChangedBy":-955361223},{"langUid":-3831212382533713919,"name":"Chitumbuka","langLocalChangeSeqNum":0,"langMasterChangeSeqNum":1,"langLastChangedBy":-892023645},{"langUid":-3831212382533713918,"name":"Wolaita","langLocalChangeSeqNum":0,"langMasterChangeSeqNum":2,"langLastChangedBy":-892023645},{"langUid":-3831212382533713917,"name":"Pawari","langLocalChangeSeqNum":0,"langMasterChangeSeqNum":3,"langLastChangedBy":-892023645},{"langUid":-3831212382533713916,"name":"siSwati","langLocalChangeSeqNum":0,"langMasterChangeSeqNum":4,"langLastChangedBy":-892023645},{"langUid":-3831212382533713915,"name":"K\u0027iche","langLocalChangeSeqNum":0,"langMasterChangeSeqNum":5,"langLastChangedBy":-892023645},{"langUid":-3831212382533713914,"name":"Mixe","langLocalChangeSeqNum":0,"langMasterChangeSeqNum":6,"langLastChangedBy":-892023645},{"langUid":-3831212382533713913,"name":"Provençal","langLocalChangeSeqNum":0,"langMasterChangeSeqNum":7,"langLastChangedBy":-892023645},{"langUid":-3831212382533713912,"name":"Gascon","langLocalChangeSeqNum":0,"langMasterChangeSeqNum":8,"langLastChangedBy":-892023645},{"langUid":-3831212382533713911,"name":"Chatino","langLocalChangeSeqNum":0,"langMasterChangeSeqNum":9,"langLastChangedBy":-892023645},{"langUid":-4103245208651557584,"name":"Pushto","iso_639_1_standard":"ps","langLocalChangeSeqNum":0,"langMasterChangeSeqNum":3570,"langLastChangedBy":-892023645},{"langUid":-4103245208651561105,"name":"Persian","iso_639_1_standard":"fa","langLocalChangeSeqNum":0,"langMasterChangeSeqNum":2836,"langLastChangedBy":-892023645},{"langUid":-4103245208651561181,"name":"English","iso_639_1_standard":"en","langLocalChangeSeqNum":0,"langMasterChangeSeqNum":1503,"langLastChangedBy":-892023645}]