<?xml version="1.0" encoding="utf-8"?>
<resources>
    <string name="app_name">‫أستاد موبايل‬</string>
    <string name="location_permission_title">مطلوب اذن للحصول على الموقع</string>
    <!--Content editor-->
    <string name="multiple_choice">متعدد الخيارات</string>
    <string name="content_font_10">10</string>
    <string name="content_source_device">من الجهاز</string>
    <string name="video">فيديو</string>
    <string name="content_untitled_document">ملف بدون عنوان</string>
    <string name="content_editor_menu_undo">تراجع</string>
    <string name="content_editor_menu_strikesthrough">يتوسطه خط</string>
    <string name="content_editor_menu_superscript">مرتفع</string>
    <string name="permission_camera_title">يلزم وجود إذن للكاميرا و الملف</string>
    <string name="content_editor_create_new_category">مجلد جديد</string>
    <string name="licence">رخصة</string>
    <string name="publicly_accessible">انشر المحتوى</string>
    <string name="content_creation_storage_option_title">خيار التخزين</string>
    <string name="file_required_prompt">الرجاء اختيار الملف المراد استيراده و المحاولة مرة اخرى</string>
    <string name="content_creation_folder_new_message">تم اضافة مستند جديد بنجاح</string>
    <string name="content_creation_folder_update_message">تم تحديث المستند بنجاح</string>
    <string name="error_message_load_page">فشل تحميل الصفحة</string>
    <string name="error_message_update_document">فشل تحديث المستند</string>
    <string name="location_permission_message">التطبيق يلزم اذن للحصول على الموقع حتى تتمكن من تحميل المحتوى و مشاركته مع الاخرين من حولك دون اتصال. لن نقوم بحفظ او قراءة الموقع، بل سنقوم باستخدام المسح عن طريق البلوتوث للبحث عن الاجهزة القريبة.</string>
    <string name="download_storage_option_device">التخزين على ذاكرة الهاتف %1$s جيجابيت متوفر
التخزين على بطاقة ذاكرة %2$s جيجابيت متوفر</string>
    <string name="content_from_file">من الملف</string>
    <string name="confirm">تأكيد</string>
    <string name="new_tab">العرض على شاشة جديدة</string>
    <string name="loading">تحميل</string>
    <string name="error_opening_file">خطأ في فتح الملف:</string>
    <string name="supported_files">الملفات المدعمة: <b>Vídeo, Audio, EPUB, Xapi Zip,H5P</b>
    </string>
    <string name="logout">تسجيل الخروج</string>
    <string name="about">حول</string>
    <string name="download_all">تنزيل الكل</string>
    <string name="previous">السابق</string>
    <string name="back">رجوع</string>
    <string name="username">اسم المستخدم</string>
    <string name="confirm_password">تأكيد كلمة السر</string>
    <string name="last_name">اسم العائلة</string>
    <string name="phone_memory">ذاكرة الهاتف</string>
    <string name="memory_card">كرت الذاكرة</string>
    <string name="device">جهاز</string>
    <string name="register">تسجيل</string>
    <string name="phone_number">رقم الهاتف</string>
    <string name="language">لغة</string>
    <string name="advanced">المتقدم</string>
    <string name="optional">اختياري</string>
    <string name="regcode">رمز التسجيل</string>
    <string name="phone">الهاتف</string>
    <string name="attendance">الحضور</string>
    <string name="classes">الحصص</string>
    <string name="exams">اختبارات</string>
    <string name="forgot_password">نسيت كلمة المرور</string>
    <string name="share_application">شارك التطبيق</string>
    <string name="share">مشاركة</string>
    <string name="downloading">جاري التنزيل</string>
    <string name="waiting">بالانتظار</string>
    <string name="passed">نجح</string>
    <string name="queued">في الدور</string>
    <string name="failed">فشل</string>
    <string name="success">نجاح</string>
    <string name="error_this_device_doesnt_support_bluetooth_sharing">نأسف، هذا الجهاز لا يدعم ارسال ملفات باستخدام البلوتوث.</string>
    <string name="share_offline_dialog_message">يمكنك مشاركة التطبيق من غير انترنت:
\n1- الاعدادات - اعدادات البلوتوث.
\n2- التأكد من ان الجهاز مرئي.</string>
    <string name="preparing">تحضير</string>
    <string name="field_required_prompt">هذا الحقل مطلوب</string>
    <string name="login">تسجيل دخول</string>
    <string name="error">خطأ</string>
    <string name="register_empty_fields">الرجاء تعبئة جميع الحقول الألزامية</string>
    <string name="register_incorrect_email">البريد الألكتروني خاطئ</string>
    <string name="err_registering_new_user">خطأ تعريف المستخدم الجديد:</string>
    <string name="wrong_user_pass_combo">كلمة المرور/المستخدم خطأ: حاول مرة اخرى.</string>
    <string name="login_network_error">خطأ في الشبكة: الرجاء التحقق من الاتصال بالانترنت.</string>
    <string name="download">تنزيل</string>
    <string name="libraries">مكتبات</string>
    <string name="recycled">تم تدويره</string>
    <string name="downloaded" value="81">تم تنزيلها</string>
    <string name="pause_download">ايقاف مؤقت للتنزيل</string>
    <string name="ok">موافق</string>
    <string name="delete">حذف</string>
    <string name="deleted">تم حذفه</string>
    <string name="deleting">يتم الحذف</string>
    <string name="next">التالي</string>
    <string name="password">كلمة مرور</string>
    <string name="new_password">كلمة مرور جديدة</string>
    <string name="name">الأسم</string>
    <string name="male">ذكر</string>
    <string name="other">آخر</string>
    <string name="unset">غير محدد</string>
    <string name="email">بريد إلكتروني</string>
    <string name="home">الصفحة الرئيسية</string>
    <string name="field_password_error_min">كلمة المرور يجب ان تتكون من 5 احرف على الاقل</string>
    <string name="filed_password_no_match">كلمة المرور غير متطابقة، حاول مرة اخرى</string>
    <string name="profile">ملف تعريف</string>
    <string name="dialog_download_from_playstore_message">الدخول و المشاركة في محتوى تعليمي من غير الاتصال بالانترنت</string>
    <string name="canceled">تم الغائه</string>
    <string name="reports">تقارير</string>
    <string name="notifications">إشعارات</string>
    <string name="account">حساب</string>
    <string name="send">ارسال</string>
    <string name="open">فتح</string>
    <string name="in_progress">قيد التقدم</string>
    <string name="completed">مكتمل</string>
    <string name="select_subtitle_video">اختار لغة الترجمة</string>
    <string name="no_subtitle">من غير ترجمة</string>
    <string name="no_video_file_found">لا يوجد ملف الفيلم</string>
    <string name="share_offline_zip_checkbox_label">ارسل في ملف مضغوط</string>
    <string name="dialog_download_from_playstore_ok">نزل الان (من غير دفع)</string>
    <string name="dialog_download_from_playstore_cancel">البقاء على الموقع</string>
    <string name="accept">القبول</string>
    <string name="also_available_in">متوفر ايضا في</string>
    <string name="onboarding_no_internet_headline">لا يوجد انترنت؟ لا يوجد مشكلة.</string>
    <string name="onboarding_no_internet_subheadline">كل شيء يعمل دون اتصال.</string>
    <string name="onboarding_offline_sharing">شارك دون اتصال</string>
    <string name="onboarding_offline_sharing_subheading">وفر الوقت والبيانات مع مشاركة فائقة السرعة دون اتصال بالإنترنت</string>
    <string name="download_summary_title">%1$s تنزيل نشط</string>
    <string name="update">تحديث</string>
    <string name="location_permission_details">التطبيق يستخدم المسح عن طريق البلوتوث و ال WiFi لايجاد مستخدمين قريبين. التطبيق سوق يقوم بوصل المستخدمين القرب لتنزيل المحتوى بسرعة عالية دون الحاجة لانترنت. يجب عليك اعطاء اذن الموقع لانه يعتمد على نتائج المسح. هذا التطبيق لا يحفظ نتائج المسح و الموقع.
\nهذا التطبيق مبني على خاصية المصدر المفتوح، التي ممكن الأطلاع عليها هنا github.com/UstadMobile/UstadMobile</string>
    <string name="download_continue_stacked_label">استمر بالتنزيل</string>
    <string name="download_continue_btn_label">استمرار</string>
    <string name="download_calculating">يتم الحساب…</string>
    <string name="download_wifi_only">WiFi فقط</string>
    <string name="download_state_download">
        <b>تنزيل</b> ما مجموعه %1$s بند، الذي سيستخدم %2$s من مساحة التخزين.</string>
    <string name="download_state_downloading">
        <b>جاري تحميل</b> ما مجموعه %1$s بند، الذي سيستخدم %2$s من مساحة التخزين.</string>
    <string name="download_pause_download">إيقاف مؤقت</string>
    <string name="download_downloading_placeholder">جاري تحميل %1$s من %2$s</string>
    <string name="download_locally_availability">متوفر عن قرب</string>
    <string name="download_cloud_availability">متوفر على السحابة</string>
    <string name="insufficient_space">مساحة التخزين المتوفرة غير كافية</string>
    <string name="download_entry_state_paused">متوقف مؤقتا</string>
    <string name="no_app_found">لا يوجد تطبيق لفتح الملف</string>
    <string name="entry_details_author">المؤلف</string>
    <string name="entry_details_license">رخصة:</string>
    <string name="female">انثى</string>
    <string name="get_app">الحصول على التطبيق</string>
    <string name="cancel">الغاء</string>
    <string name="settings">الإعدادات</string>
    <string name="onboarding_get_started_label">بدء الاستخدام</string>
    <string name="download_cancel_label">الغاء التنزيل</string>
    <string name="file_not_found">الملف غير موجود</string>
    <string name="first_name">الاسم الأول</string>
    <string name="download_state_downloaded">
        <b>تم تنزيل</b> ما مجموعه %1$s بند، الذي سيستخدم %2$s من مساحة التخزين.</string>
    <string name="content_editor_save_error">خطأ اثناء الحفظ، حاول مرة اخرى</string>
    <string name="content_entry_export_inprogress">جاري التصدير</string>
    <string name="invalid_register_code">رمز التسجيل غير صحيح</string>
    <string name="enter_register_code">ادخل رمز التسجيل</string>
    <string name="bar_chart" value="100">شريط تخطيط</string>
    <string name="content_entry_export_message">سوف تقوم بتصدير %1$s لسعة تخزين جهازك. هل تريد الاستمرار؟</string>
    <string name="score" value="200">معدل الناتج</string>
    <string name="xapi_day" value="300">يوم</string>
    <string name="xapi_week" value="301">اسبوع</string>
    <string name="xapi_month" value="302">شهر</string>
    <string name="xapi_custom_date" value="303">تاريخ مخصص</string>
    <string name="xapi_content_entry" value="304">ادخال المحتوى</string>
    <string name="xapi_clear">إلغاء تحديد</string>
    <string name="from">من</string>
    <string name="done">انهاء</string>
    <string name="xapi_options_general">عام</string>
    <string name="xapi_options_report_title">عنوان التقرير</string>
    <string name="xapi_options_visual_type">نوع العرض المصوّر</string>
    <string name="xapi_options_axes">احداثيات</string>
    <string name="xapi_options_y_axes">احداثي ص</string>
    <string name="xapi_options_x_axes">احداثي س</string>
    <string name="xapi_options_subgroup">مجموعة فرعية</string>
    <string name="xapi_options_filters">تصفية</string>
    <string name="xapi_options_who">من</string>
    <string name="xapi_options_did">قام بعمل</string>
    <string name="xapi_options_what">ماذا</string>
    <string name="xapi_options_when">متى</string>
    <string name="xapi_options_where">اين</string>
    <string name="activity_import_link">استيراد الرابط</string>
    <string name="xapi_hours">ساعات</string>
    <string name="xapi_minutes">دقائق</string>
    <string name="xapi_seconds">ثواني</string>
    <string name="xapi_verb_header">فعل ماذا</string>
    <string name="xapi_result_header">نتيجة</string>
    <string name="xapi_score">نتيجة (%)</string>
    <string name="import_title_not_entered">عنوان غير مدخل</string>
    <string name="no_account">ليس لديك حساب؟</string>
    <string name="enter_url">ادخل URL</string>
    <string name="import_link_content_not_supported">المحتوى غير مدعم</string>
    <string name="import_link_big_size">حجم الملف كبير</string>
    <string name="import_link_error">خطأ استيراد</string>
    <string name="offline_sharing_enable_bluetooth_prompt">المشاركة من غير انترنت يتطلب البلوتوث</string>
    <string name="offline_sharing_enable_wifi_promot">المشاركة من غير انترنت يتطلب ان يكون ال WiFi مفعل</string>
    <string name="enable">تمكين</string>
    <string name="more_information">معلومات اكثر</string>
    <string name="repo_loading_status_loading_cloud">التحميل جاري من السحابة</string>
    <string name="repo_loading_status_loading_mirror">التحميل من النظير</string>
    <string name="repo_loading_status_failed_noconnection">لا يوجد اتصال أو نظير</string>
    <string name="repo_loading_status_failed_connection_error">خطأ بالأتصال</string>
    <string name="content_from_link">من الرابط</string>
    <string name="average">المعدل</string>
    <string name="date">التاريخ</string>
    <string name="export">تصدير</string>
    <string name="at_risk_students">الطلبة في مجال الخطر</string>
    <string name="show_student_numbers">عرض أرقام الطلبة</string>
    <string name="last_three_months">آخر ثلاث شهور</string>
    <string name="location">الموقع</string>
    <string name="time_period">الفترة الزمنية</string>
    <string name="yes_no">نعم / لا</string>
    <string name="frequency">التكرار</string>
    <string name="measurement_type">نوع المقياس</string>
    <string name="select_one">إختر واحدة</string>
    <string name="add_activity_literal">أضف نشاط</string>
    <string name="add_activity">أضف نشاط جديد ...</string>
    <string name="uom_default_title">وحدة القياس</string>
    <string name="uom_boolean_title">صح أم خطأ</string>
    <string name="uom_duration_title">‏الفترة الزمنية</string>
    <string name="uom_frequency_title">كم عدد المرات</string>
    <string name="activity_enter_any_notes">أدخل أي ملاحظات لديك حول هذا النشاط</string>
    <string name="activity_went_bad">لم يجري النشاط بشكل جيد</string>
    <string name="activity_went_good">جرى النشاط بشكل جيد</string>
    <string name="down">أسفل</string>
    <string name="up">أعلى</string>
    <string name="teachers_literal">مدرسين</string>
    <string name="partial">جزئي</string>
    <string name="teacher">مدرس</string>
    <string name="attendance_low_to_high">الحضور (من الأدنى للأعلى)</string>
    <string name="attendance_high_to_low">الحضور (من الأعلى للأدنى)</string>
    <string name="sort_by_text">الترتيب حسب</string>
    <string name="sort_by_name">الترتيب حسب الأسم</string>
    <string name="activity">نشاط</string>
    <string name="notes">ملاحظات</string>
    <string name="how_did_it_go">كيف سارت الأمور؟</string>
    <string name="duration">الفترة الزمنية</string>
    <string name="change_implemented_if_any">التغيير الذي جرى (أن حصل)</string>
    <string name="activity_change">تغيير النشاط</string>
    <string name="last_month">الشهر الماضي</string>
    <string name="toC">الى</string>
    <string name="day">يوم</string>
    <string name="may">مايو</string>
    <string name="saturday">السبت</string>
    <string name="friday">الجمعة</string>
    <string name="thursday">الخميس</string>
    <string name="wednesday">الأربعاء</string>
    <string name="tuesday">الثلاثاء</string>
    <string name="monday">الإثنين</string>
    <string name="sunday">الأحد</string>
    <string name="yearly">سنوي</string>
    <string name="monthly">شهري</string>
    <string name="daily">كل يوم عمل</string>
    <string name="once">مرة واحدة</string>
    <string name="weekly">أسبوعي</string>
    <string name="class_setup">إعداد الفصل</string>
    <string name="features_enabled">الميزات المتاحة</string>
    <string name="holiday_calendar">تقويم الإجازات</string>
    <string name="to">الى</string>
    <string name="class_description">وصف الفصل</string>
    <string name="class_name">أسم الفصل</string>
    <string name="add_class">أضف فصل</string>
    <string name="add_person">أضف شخص</string>
    <string name="questions">أسئلة</string>
    <string name="question">سؤال</string>
    <string name="sel">التعليم الإجتماعي والعاطفي SEL</string>
    <string name="student_image">صورة الطالب</string>
    <string name="clazz">فصل</string>
    <string name="edit">تعديل</string>
    <string name="edit_person">تعديل بيانات شخص</string>
    <string name="add_person_to_class">إضافة شخص للفصل</string>
    <string name="basic_details">التفاصيل الأساسية</string>
    <string name="first_names">الأسماء الأولى</string>
    <string name="birthday">يوم الميلاد</string>
    <string name="mother">أم</string>
    <string name="father">أب</string>
    <string name="attendance_report">تقرير الحضور</string>
    <string name="absent_selected">إختيار الغائبين</string>
    <string name="absent">غائب</string>
    <string name="present">حاضر</string>
    <string name="mark_all_absent">ضع علامة على جميع الغائبين</string>
    <string name="mark_all_present">ضع علامة على جميع الحاضرين</string>
    <string name="mark_all">ضع علامة على الجميع</string>
    <string name="last_week">الأسبوع الماضي</string>
    <string name="last">الأخير</string>
    <string name="first">الأول</string>
    <string name="schedule">جدول</string>
    <string name="log">سجل</string>
    <string name="sort_by">الفرز عن طريق</string>
    <string name="today">اليوم</string>
    <string name="record_attendance">سجل الحضور</string>
    <string name="people">اشخاص</string>
    <string name="feed">تغذية</string>
    <string name="store_description_full">استاد موبايل هو تطبيق موارد مفتوحة الذي يمكن المستخدمين من الدخول الى مصاددر تعليمية، ةع ومن دون الأتصال بالأنترنت. يستطيع المستخدم مشاركة المحتوى و التطبيق مع الأخرين من دون الأتصال بالأنترنت.
\n
\nاستاد موبايل يوفر محتوى مرخص من مصادر تعليمية مفتوحة من مواقع رائجة على الأنترنت:
\n
\nأفريكان ستوري بوكس
\nأيتيكاثو
\nجلوبل ديجيتل لايبرري
\nخان أكاديمي (توفر فيديو و نشاطات دون الأتصال بالأنترنت)
\nPHET
\nبراثام بوكس
\nفويس اوف امريكا
\n
\nالمحتوى متوفر تحت رخصة من موفريين محتوى خارجي. أستاد موبايل .</string>
    <string name="permission_activity_insert">أخذ نشاط الصف</string>
    <string name="date_left">تاريخ متبقي</string>
    <string name="store_description_short">ادخل و شارك محتوى تعليمي دون اتصال</string>
    <string name="store_title">أستاد موبايل - موارد تعليمية دون اتصال</string>
    <string name="mixed">مختلط</string>
    <string name="started">بدأ</string>
    <string name="started_date">بدأ ب %1$s</string>
    <string name="percentage_complete">%1$s%% اكتمل</string>
    <string name="not_started">لم يبدأ</string>
    <string name="instructions_for_students">تعليمات للطلاب</string>
    <string name="None">لا شيء</string>
    <string name="new_assignment">أضف واجب</string>
    <string name="assignments">واجبات</string>
    <string name="schools">مدارس</string>
    <string name="refresh">تحديث</string>
    <string name="add">إضافة</string>
    <string name="users_settings_desc">أضافة، وألغاء، وتعديل المستخدمين، أو أعادة تعيين كلمة السر الخاصة فيهم</string>
    <string name="last_synced_at">اخر مزامنة</string>
    <string name="select_a_timezone">أختر وحدة زمنية</string>
    <string name="password_unchanged">كلمة السر (دون تغيير)</string>
    <string name="current_password">كلمة السر الحالية</string>
    <string name="change_password">تغيير كلمة السر</string>
    <string name="save">حفظ</string>
    <string name="end_date">تاريخ الأنتهاء</string>
    <string name="start_date">تاريخ البدء</string>
    <string name="feedback_thanks">شكرا لأرسال التغذية الراجعة.</string>
    <string name="send_feedback">أرسال التغذية الراجعة</string>
    <string name="feedback_hint">الرجاء ادخال التغذية الراجعة</string>
    <string name="shake_feedback">هز الجهاز للتغذية الراجعة</string>
    <string name="errors">أخطاء</string>
    <string name="option_value">قيمة الخيار</string>
    <string name="options">خيارات</string>
    <string name="dropdown">قائمة</string>
    <string name="text">نص</string>
    <string name="field_type">نوع الحقل</string>
    <string name="custom_fields_desc">أضافة، حذف، او تعديل الحقل المخصص</string>
    <string name="custom_field">حقل مخصص</string>
    <string name="custom_fields">حقل مخصص</string>
    <string name="permission_sel_question_insert">أضف أسئلة التعلم الأجتماعي العاطفي</string>
    <string name="permission_sel_question_select">عرض أسئلة التعلم الأجتماعي العاطفي</string>
    <string name="permission_sel_update">تحديث نتائج التعلم الأجتماعي العاطفي</string>
    <string name="permission_sel_select">عرض نتائج التعلم الأجتماعي العاطفي</string>
    <string name="permission_sel_question_update">تحديث أسئلة التعلم الأجتماعي العاطفي</string>
    <string name="permission_activity_update">تحديث نشاط الصف</string>
    <string name="permission_activity_select">عرض نشاط الصف</string>
    <string name="permission_attendance_update">تحديث الحضور</string>
    <string name="permission_attendance_insert">أخذ الحضور</string>
    <string name="permission_attendance_select">عرض الحضور</string>
    <string name="permission_clazz_add_student">أضف طلاب للصف</string>
    <string name="permission_clazz_add_teacher">أضف معلمات للصف</string>
    <string name="permission_clazz_update">تحديث الحصص</string>
    <string name="permission_clazz_insert">اضافة الحصص</string>
    <string name="permission_clazz_select">عرض الحصص</string>
    <string name="permission_person_picture_update">تحديث صورة ملف التعرف</string>
    <string name="permission_person_picture_insert">أضف صورة لملف التعرف</string>
    <string name="permission_person_picture_select">عرض صورة ملف التعرف</string>
    <string name="permission_person_update">تحديث الأشخاص</string>
    <string name="permission_person_insert">أضف أشخاص</string>
    <string name="permission_person_select">عرض الأشخاص</string>
    <string name="person">شخص</string>
    <string name="add_edit_location">أضافة و تعديل الوقع</string>
    <string name="assign_to">تعيين ل</string>
    <string name="scope_by">النطاق</string>
    <string name="role_assignment">تعيين دور</string>
    <string name="new_group">مجموعة جديدة</string>
    <string name="add_group">أضف مجموعة</string>
    <string name="member">عضو</string>
    <string name="members">أعضاء</string>
    <string name="role_name">اسم الدور</string>
    <string name="permission">إذن</string>
    <string name="permissions">أذونات وصول</string>
    <string name="entry">إدخال</string>
    <string name="audit_log_setting_desc">مشاهدة و تصدير سجل التدقيق</string>
    <string name="audit_log">سجل التدقيق</string>
    <string name="locations_setting_desc">إدارة المواقع</string>
    <string name="locations">مواقع</string>
    <string name="role_assignment_setting_desc">تعيين دور لمستخدم او مجموعة</string>
    <string name="rols_assignment">تعيين الأدوار</string>
    <string name="role">دور</string>
    <string name="roles">أدوار</string>
    <string name="group_setting_desc">اضف، الغي او عدل على المجموعات</string>
    <string name="groups">مجموعات</string>
    <string name="dropout_reason_move">نقل</string>
    <string name="not_recorded">غير مسجل</string>
    <string name="sync">مزامنة</string>
    <string name="over">عبر</string>
    <string name="filter">تصفية</string>
    <string name="attendance_percentage">نسبة الحضور:</string>
    <string name="search">بحث</string>
    <string name="sel_question_set_to_use">السؤال المحدد للأستعمال</string>
    <string name="gender_literal">الجنس</string>
    <string name="class_id">معرف الصف</string>
    <string name="active">نشط</string>
    <string name="nomination">تصويت</string>
    <string name="add_option">إضافة خيار</string>
    <string name="sel_question_type_free_text">نص حر</string>
    <string name="question_type">نوع السؤال</string>
    <string name="question_text">نص السؤال</string>
    <string name="edit_question">تعديل سؤال</string>
    <string name="users">مستخدمين</string>
    <string name="sel_question_set_desc">ادارة مجموعة الأسئلة</string>
    <string name="sel_question_set">مجموعة الأسئلة</string>
    <string name="holiday_calendars_desc">اضافة، الغاء، و تعديل تقويم العطل</string>
    <string name="holiday_calendars">تقويم العطل</string>
    <string name="all">الكل</string>
    <string name="file_selected">الملف المختار:</string>
    <string name="apply">تطبيق</string>
    <string name="days">أيام</string>
    <string name="age">عمر</string>
    <string name="sort_by_name_desc">الأسم (تنازلي)</string>
    <string name="sort_by_name_asc">الأسم (تصاعدي)</string>
    <string name="syncing">مزامنة..</string>
    <string name="students">طلاب</string>
    <string name="contents">المحتوى</string>
    <string name="licence_type_cc_by_sa_nc">نَسب المُصنَّف - غير تجاري - الترخيص بالمثل</string>
    <string name="licence_type_cc_by_nc_sa">نَسب المُصنَّف - غير تجاري - الترخيص بالمثل</string>
    <string name="licence_type_cc_by_nc">نسب المصنف - غير تجاري</string>
    <string name="licence_type_cc_by_sa">نَسب المُصنَّف - الترخيص بالمثل</string>
    <string name="licence_type_cc_by">نَسب المُصنَّف</string>
    <string name="three_num_items_with_name_with_comma">%1$d %2$s, %3$d %4$s, %5$d %6$s</string>
    <string name="x_percent_attended">%1.0f%% حضور</string>
    <string name="present_late_absent">%1$d حضور، %2$d متأخر، %3$d غياب</string>
    <string name="x_teachers_y_students">%1$d معلمين، %2$d طلاب</string>
    <string name="items_selected">%1$d مختار</string>
    <string name="remove_from">ازالة من %1$s</string>
    <string name="add_to">اضف الى %1$s</string>
    <string name="num_items_with_name_with_comma">%1$d %2$s, %3$d %4$s</string>
    <string name="num_items_with_name">%1$d %2$s</string>
    <string name="from_to_date">%1$s - %2$s</string>
    <string name="select_item">%1$s اختر</string>
    <string name="id_verbentity_urlid">رقم تعريفي: s%</string>
    <string name="class_timezone">المنطقة الزمنية للصف</string>
    <string name="student_progress">تقدم الطالب</string>
    <string name="timezone">منطقة زمنية</string>
    <string name="licence_type_public_domain">مجال عام</string>
    <string name="dashboard">لوحة معلومات</string>
    <string name="entry_details_publisher">ناشر</string>
    <string name="created_partnership">تم انشائه بالتعاون مع:</string>
    <string name="import_content">استيراد المحتوى</string>
    <string name="return_only">ارجاع و انهاء</string>
    <string name="return_and_mark_next">ارجاع و تعليم التالي</string>
    <string name="marking">علامة</string>
    <string name="submit">ارسال</string>
    <string name="class_comments">تعليقات الصف</string>
    <string name="add_private_comment">اضف تعليق خاص</string>
    <string name="add_class_comment">اضف تعليق للصف</string>
    <string name="submit_your_answer">ارسال جوابك</string>
    <string name="private_comments">تعليقات خاصة</string>
    <string name="public_comments">تعليقات عامة</string>
    <string name="submission">عمليات الإرسال</string>
    <string name="time">وقت</string>
    <string name="quiz_questions">اسئلة الاختبار القصير</string>
    <string name="maximum_score">الدرجة القصوى</string>
    <string name="deadline">الموعد النهائي</string>
    <string name="allow_private_comments_from_students">عرض التعليقات الخاصة من الطلاب</string>
    <string name="quiz">اختبار</string>
    <string name="attachment">مرفق</string>
    <string name="short_text">نص قصير</string>
    <string name="no_submission_required">عملية الارسال غير ملزمة</string>
    <string name="submission_type">نوع عمليات الارسال</string>
    <string name="visible_from_date">واضح من التاريخ</string>
    <string name="not_submitted">لم يتم ارساله</string>
    <string name="submitted">تم ارساله</string>
    <string name="marked">محدد</string>
    <string name="clazz_work">واجب</string>
    <string name="nothing_here">لا يوجد شيء</string>
    <string name="untitled">غير معنون</string>
    <string name="contact_details">تفاصيل جهة الاتصال</string>
    <string name="student">طالب</string>
    <string name="organization_id">الرقم التعريفي للمنظمة</string>
    <string name="call">اتصل</string>
    <string name="staff">فريق العمل</string>
    <string name="add_new">اضف جديد</string>
    <string name="overview">نظرة عامة</string>
    <string name="permission_clazz_asignment_edit">انشاء و تعديل واجبات الصف</string>
    <string name="permission_clazz_assignment_view">عرض واجبات الصف</string>
    <string name="select_new_photo_from_gallery">اختيار صورة جديدة من معرض الصور</string>
    <string name="take_new_photo_from_camera">التقاط صورة جديدة بواسطة الكاميرا</string>
    <string name="remove_photo">ازالة الصورة</string>
    <string name="change_photo">تغيير الصورة</string>
    <string name="use_device_language">استخدم لغة الجهاز</string>
    <string name="content">محتوى</string>
    <string name="due_date">تاريخ التسليم</string>
    <string name="school">مدرسة</string>
    <string name="holidays">عطل</string>
    <string name="holiday">عطلة</string>
    <string name="address">عنوان</string>
    <string name="licence_type_all_rights">جميع الحقوق محفوظة</string>
    <string name="verb">فعل</string>
    <string name="report">تقرير</string>
    <string name="preview">عرض</string>
    <string name="audio">صوت</string>
    <string name="article">مقال</string>
    <string name="document">مستند</string>
    <string name="collection">مجموعة</string>
    <string name="interactive">تفاعلي</string>
    <string name="ebook">كتاب الكتروني</string>
    <string name="title">عنوان</string>
    <string name="update_content">تعديل المحتوى</string>
    <string name="select_language">اختر لغة</string>
    <string name="description">وصف</string>
    <string name="sel_question_type_multiple_choice">اختيار من متعدد</string>
    <string name="incorrect_current_password">كلمة السر خاطئة</string>
    <string name="person_exists">الشخص مسجل، اختر اسم مستخدم آخر</string>
    <string name="logged_in_as">التسجيل ك %1$s على %2$s</string>
    <string name="add_another">اضف %1$s آخر</string>
    <string name="my">%1$s ي</string>
    <string name="create_account">انشاء حساب</string>
    <string name="connect_as_guest">الاتصال كضيف</string>
    <string name="create_site">انشاء مساحة عمل جديدة للمنظمة</string>
    <string name="use_public_library_site">استخدم المكتبة العامة</string>
    <string name="organisation">%1$s منظمة</string>
    <string name="workspace">مساحة عمل</string>
    <string name="not_answered">لم يتم الاجابة</string>
    <string name="of_content">من المحتوى</string>
    <string name="answer">جواب</string>
    <string name="submitliteral">قم بالارسال</string>
    <string name="not_submitted_cap">لم يتم ارسال</string>
    <string name="submitted_cap">تم الارسال</string>
    <string name="marked_cap">تم وضع العلامة</string>
    <string name="descending">تنازلي</string>
    <string name="ascending">تصاعدي</string>
    <string name="invalid_link">رابط غير صالح</string>
    <string name="lets_get_started_label">لنبدأ</string>
    <string name="accounts">حسابات</string>
    <string name="register_now">سجل الان</string>
    <string name="license_type_cc_0">الحقوق غير محفوظة</string>
    <string name="ask_your_teacher_for_code">اسأل معلمك عن الرمز ، ثم أدخله أدناه:</string>
    <string name="reject">رفض</string>
    <string name="pending_requests">الطلبات المعلقة</string>
    <string name="class_code">رمز الصف</string>
    <string name="copied_to_clipboard">تم النسخ</string>
    <string name="please_wait_for_approval">الرجاء الانتظار لموافقة طلبك من المعلمة.</string>
    <string name="pending">في الانتظار</string>
    <string name="permission_password_reset">اعادة تعيين و تحديث كلمة السر</string>
    <string name="permission_person_delegate">توكيل الادوار و الاذونات للاخرين</string>
    <string name="invite_with_link">الدعوه عن طريق الرابط</string>
    <string name="invite_link_desc">اس شخص يملك الرابط يمكن المشاركة او التسجيل للمشاركة. يمكنك الموافقة او الرفض لاحقا.</string>
    <string name="role_description">الدور (مثال معلمة، طالب الخ) يعطي مجموعة من الاذونات (مثال شاهد تفاصيل الاشخاص، تسجيل الحضور الخ) و ذلك يطبق على المجال المختار في الاعلى.</string>
    <string name="scope_description">اختر المجال (مثال صف، مدرسة، او شخص) الذي سيطبق عليه الاذن.</string>
    <string name="scope">مجال</string>
    <string name="add_role_permission">اضف دور و اذن</string>
    <string name="roles_and_permissions">الادوار و اذونات</string>
    <string name="record_for_student">سجل للطالب</string>
    <string name="join_code_instructions">اطلب من معلمتك الرمز، ثو ادخله بالاسفل:</string>
    <string name="entity_code">رمز</string>
    <string name="school_code">رمز المدرسة</string>
    <string name="add_staff_to_school">اضف الطاقم الى المدرسة</string>
    <string name="add_student_to_school">اضف طالب الى المدرسة</string>
    <string name="permission_school_update">تحديث و تعديل المدارس الموجودة</string>
    <string name="permission_school_insert">اضف مدرسة جديدة</string>
    <string name="permission_school_select">مشاهدة و اختيار المدارس</string>
    <string name="permission_role_insert">ادخل دور جديد</string>
    <string name="permission_role_select">شاهد و اختار كل الادوار</string>
    <string name="this_field_is_mandatory">الحقل اجباري</string>
    <string name="role_not_selected_error">يجب اختيار الدور</string>
    <string name="share_link">شارك الرمز</string>
    <string name="copy_code">انسخ الرمز</string>
    <string name="copy_link">انسخ الرابط</string>
    <string name="assign_role">تحديد الدور</string>
    <string name="edit_clazzwork">تعديل الواجب</string>
    <string name="add_a_new_clazzwork">اضف واجب جديد</string>
    <string name="status">الحالة</string>
    <string name="add_content">اضف محتوى</string>
    <string name="add_new_content">اضف محتوى جديد</string>
    <string name="join_existing_school">المشاركة في مدرسة موجودة</string>
    <string name="edit_school">تعديل المدرسة</string>
    <string name="add_a_new_school">اضف مدرسة جديدة</string>
    <string name="add_a_new_person">اضف شخص جديد</string>
    <string name="edit_role">تعديل الدور</string>
    <string name="add_a_new_role">اضف دور جديد</string>
    <string name="primary_user">مستخدم رئيسي</string>
    <string name="participant">مشارك</string>
    <string name="add_a_teacher">اضف معلم</string>
    <string name="date_enroll">تاريخ التسجيل</string>
    <string name="edit_holiday_calendar">تعديل رزنامة العطل</string>
    <string name="add_a_new_holiday_calendar">اضف رزنامة عطل جديدة</string>
    <string name="edit_holiday">تعديل العطلة</string>
    <string name="add_a_holiday">اضف عطلة</string>
    <string name="add_question">اضف سؤال</string>
    <string name="join_existing_class">المشاركة في صف موجود</string>
    <string name="add_a_class">اضف حصة</string>
    <string name="edit_clazz">التعديل على الصف</string>
    <string name="add_a_new_class">اضف صف جديد</string>
    <string name="edit_schedule">التعديل على جدول المواعيد</string>
    <string name="add_a_schedule">اضف جدول مواعيد</string>
    <string name="supported_link">انواع الروابط المدعومة: Google Drive (ملف او مجلد) و روابط</string>
    <string name="add_content_filter">اضف تصنيف المحتو</string>
    <string name="add_verb_filter">اضف تصنيف للافعال</string>
    <string name="add_person_filter">اضف تصنيف للاشخاص</string>
    <string name="add_a_new_verb">اضف فعل جديد</string>
    <string name="edit_report">تعديل التقرير</string>
    <string name="create_a_new_report">انشاء تقرير جديد</string>
    <string name="underRegistrationAgeError">التسجيل الذاتي للاطفال تحت التلاتة عشر سنة غير مسموح. الرجاء الطلب من المعلمة للتسجيل.</string>
    <string name="add_a_student">اضف طالب</string>
    <string name="add_a_new_language">اضف لغة جديدة</string>
    <string name="select_group_members">اختر اعضاء المجموعة</string>
    <string name="group_activity">مجموعة
\nنشاط</string>
    <string name="year">سنة</string>
    <string name="last_month_date_range">الشهر الماضي</string>
    <string name="last_three_months_date_range">الأشهر الثلاثة الماضية</string>
    <string name="choose_template">اختيار القالب</string>
    <string name="new_custom_date_range">نطاق زمني مخصص جديد …</string>
    <string name="add_link_description">أضف محتوى تعليميًا باستخدام رابط الويب ، ثم استخدمه في وضع عدم الاتصال</string>
    <string name="add_gallery_description">أضف مقطع فيديو أو صوتًا من معرض الجهاز</string>
    <string name="xapi_options_data_set">مجموعة البيانات</string>
    <string name="xapi_options_series">مسلسل</string>
    <string name="enter_link">أدخل الارتباط</string>
    <string name="unhide">إظهار</string>
    <string name="compress">ضغط</string>
    <string name="show_hidden_items">إظهار العناصر المخفية</string>
    <string name="open_folder">افتح المجلد</string>
    <string name="line_chart">خط الرسم البياني</string>
    <string name="content_total_duration">استخدام المحتوى - المدة الإجمالية</string>
    <string name="content_average_duration">استخدام المحتوى - متوسط المدة لكل جلسة</string>
    <string name="interaction_recorded">استخدام المحتوى - عدد التفاعلات المسجلة</string>
    <string name="number_active_users">استخدام المحتوى - عدد المستخدمين النشطين</string>
    <string name="time_range_all">كل شىء</string>
    <string name="report_filter_edit_field">مجال</string>
    <string name="report_filter_edit_condition">شرط</string>
    <string name="report_filter_edit_values">قيم)</string>
    <string name="field_content_completion">حالة اكتمال المحتوى</string>
    <string name="field_content_entry">إدخال المحتوى</string>
    <string name="field_content_progress">تقدم المحتوى</string>
    <string name="field_attendance_percentage">نسبة الحضور</string>
    <string name="condition_is">هو</string>
    <string name="condition_greater_than">أكثر من</string>
    <string name="condition_less_than">أقل من</string>
    <string name="condition_in_list">في قائمة</string>
    <string name="condition_not_in_list">ليس في القائمة</string>
    <string name="country">دولة</string>
    <string name="home_internet_access">الوصول إلى الإنترنت في المنزل</string>
    <string name="mobile_internet_access">الوصول إلى الإنترنت عبر الهاتف المحمول</string>
    <string name="connectivity_limited">محدود - أتجنب تنزيل الكثير</string>
    <string name="connectivity_full">ممتلئ - أقوم بالتنزيل بقدر ما أريد</string>
    <string name="prefer_not_to_say">افضل عدم القول</string>
    <string name="this_class">هذه الفئة</string>
    <string name="last_active">آخر نشاط</string>
    <string name="fixed_date">التاريخ المحدد</string>
    <string name="relative_date">التاريخ النسبي</string>
    <string name="subjects">المواضيع</string>
    <string name="moved_x_entries">تم نقل %1$s إدخالات</string>
    <string name="end_is_before_start_error">النهاية قبل البدء</string>
    <string name="record_attendance_for_most_recent_occurrence">سجل الحضور لأحدث حدث موجود</string>
    <string name="site_link">رابط الموقع</string>
    <string name="please_enter_the_linK">الرجاء إدخال رابط بيئة التعلم الخاصة بك التي قدمها معلمك أو المسؤول:</string>
    <string name="or">أو</string>
    <string name="terms_and_policies_text">نص الشروط والسياسات</string>
    <string name="edit_terms_and_policies">تحرير الشروط والسياسات</string>
    <string name="strings_not_allowed">الأحرف الخاصة غير مسموح بها في هذا المجال</string>
    <string name="undo">الغاء التحميل</string>
    <string name="content_pieces_completed">أجزاء المحتوى اكتملت</string>
    <string name="content_usage_duration">مدة استخدام المحتوى</string>
    <string name="manage_download">إدارة التنزيل</string>
    <string name="select_account_to_continue">حدد الحساب للمتابعة</string>
    <string name="you_are_already_in_class">خطأ: أنت مسجل بالفعل في الفصل الدراسي: %1$s</string>
    <string name="looks_like_installed_app_from_link">يبدو أنك قمت للتو بتثبيت التطبيق باستخدام رابط. ماذا تريد ان تفعل؟</string>
    <string name="join_school">انضم إلى المدرسة</string>
    <string name="we_sent_a_message_to_your_parent">لقد أرسلنا رسالة إلى والديك ( %1$s) حتى يتمكنوا من الموافقة على تسجيلك. يمكنك تسجيل الدخول باستخدام اسم المستخدم وكلمة المرور اللذين قمت بتعيينهما بعد موافقة والديك.</string>
    <string name="toggle_visibility">تبديل الرؤية</string>
    <string name="parental_consent">موافقة الوالدين</string>
    <string name="parent_child_register_message_subject">ولي الأمر - يُرجى الموافقة على تسجيل طفلك لدى %1$s أو رفضه</string>
    <string name="i_consent">أنا موافق</string>
    <string name="i_do_not_consent">أنا لا أوافق</string>
    <string name="revoke_consent">إبطال الموافقة</string>
    <string name="restore_consent">استعادة الموافقة</string>
    <string name="status_consent_denied">الحالة: تم رفض الموافقة (%1$s)</string>
    <string name="other_legal_guardian">وصي قانوني آخر</string>
    <string name="manage_parental_consent">إدارة موافقة الوالدين</string>
    <string name="view_class_content">عرض محتوى الفصل</string>
    <string name="edit_class_content">تحرير محتوى الفصل</string>
    <string name="view_contact_details_of_members">عرض تفاصيل الاتصال الأعضاء</string>
    <string name="edit_contact_details_of_members">تحرير تفاصيل الاتصال العضو</string>
    <string name="view_socioeconomic_details_of_members">عرض التفاصيل الاجتماعية والاقتصادية للأعضاء</string>
    <string name="add_person_or_group">أضف شخصًا أو مجموعة</string>
    <string name="continue_using_link_recommended">الاستمرار في استخدام الرابط (موصى به)</string>
    <string name="continue_using_the_link">استمر في استخدام الرابط المقدم للانضمام إلى فصل دراسي أو مدرسة.</string>
    <string name="ignore_the_link">تجاهل الارتباط والاستمرار في تسجيل الدخول الافتراضي</string>
    <string name="add_permission_for_a_person">إضافة إذن لشخص</string>
    <string name="add_permission_for_a_group">إضافة إذن لمجموعة</string>
    <string name="add_video_or_audio_from_the_device_gallery">أضف مقطع فيديو أو صوتًا من معرض الجهاز</string>
    <string name="add_file">اضف ملف</string>
    <string name="add_educational_content_using_supported_formats_eg_pdf_xapi_h5p">أضف محتوى تعليميًا باستخدام التنسيقات المدعومة مثل PDF و xAPI و H5P</string>
    <string name="add_subject">إضافة الموضوع</string>
    <string name="share_via">شارك عبر…</string>
    <string name="share_apk_file">مشاركة ملف APK</string>
    <string name="recommended_for_advanced_users">يوصى به للمستخدمين المتقدمين</string>
    <string name="recommended_for_offline_installation">موصى به للتثبيت في وضع عدم الاتصال</string>
    <string name="app_store_link">رابط متجر التطبيقات</string>
    <string name="everything_works_offline">كل شيء يعمل دون اتصال.</string>
    <string name="content_usage_time">وقت استخدام المحتوى</string>
    <string name="all_permissions">كل الأذونات</string>
    <string name="folder">مجلد</string>
    <string name="create_a_new_learning_env">خلق بيئة تعليمية جديدة</string>
    <string name="connect_to_an_existing_learning_environment">الاتصال ببيئة التعلم الحالية</string>
    <string name="does_your_class_already_have_learning_env">هل يوجد بالفعل في صفك أو مدرستك أو مؤسستك بيئة تعليمية؟ رائعة!</string>
    <string name="revoking_consent_will">سيؤدي إلغاء الموافقة إلى حذف البيانات الشخصية للطفل في غضون 24 ساعة</string>
    <string name="you_must_comply_with_license">يجب عليك التأكد من امتثالك لشروط ترخيص المحتوى</string>
    <string name="you_can_copypaste_a_link">يمكنك نسخ/لصق رابط من مواقع تعليمية مختلفة.</string>
    <string name="total_score">مجموع النقاط</string>
    <string name="anyone_with_this_can_join_school">يمكن لأي شخص لديه هذا الرابط التقدم للانضمام إلى المدرسة. يمكنك الموافقة أو رفض طلبهم للانضمام</string>
    <string name="from_my_classes">من فصولي</string>
    <string name="my_content">المحتوى الخاص بي</string>
    <string name="learning_environment">بيئة التعلم</string>
    <string name="grades_class_age">درجات</string>
    <string name="add_remove_and_modify_subjects">إضافة وإزالة وتعديل الموضوعات</string>
    <string name="create_my_account">إنشيء حسابي</string>
    <string name="recommend_it">أوصي به</string>
    <string name="edit_permissions">تحرير الأذونات</string>
    <string name="almost_done">يكاد ينتهي!</string>
    <string name="your_username">اسم المستخدم الخاص بك</string>
    <string name="select_content">حدد المحتوى</string>
    <string name="search_in">بحث في</string>
    <string name="type">يكتب</string>
    <string name="please_download_the_app">الرجاء تنزيل التطبيق</string>
    <string name="alternatively_you_can_download_the_apk">بدلاً من ذلك ، يمكنك تنزيل ملف APK للتثبيت اليدوي إذا كنت تريد ذلك.</string>
    <string name="full_i_can_download_as_much_as_i_like">ممتلئ - يمكنني التنزيل بقدر ما أحب</string>
    <string name="limited_i_avoid_downloading_too_much">محدود - أتجنب تنزيل الكثير</string>
    <string name="oops">وجه الفتاة!</string>
    <string name="incident_id">رقم الحدث</string>
    <string name="error_code">رمز الخطأ: %1$s</string>
    <string name="take_me_home">خذنى إلى المنزل</string>
    <string name="view_clazz">مشاهدة الفصل</string>
    <string name="view_clazzes">مشاهدة الفصول الدراسية</string>
    <string name="enrol_and_unenrol_students">تسجيل الطلاب وإلغاء تسجيلهم</string>
    <string name="enrol_and_unenrol_teachers">تسجيل وإلغاء تسجيل المعلمين</string>
    <string name="view_assignments">عرض الواجبات</string>
    <string name="add_or_edit_assignment">إضافة أو تحرير الواجبات</string>
    <string name="edit_basic_profile_of_members">تحرير ملف التعريف الأساسي للأعضاء</string>
    <string name="view_school">مشاهدة المدرسة</string>
    <string name="edit_clazzes">تحرير الفصول الدراسية</string>
    <string name="graduated">تخرج</string>
    <string name="enroled">المسجلين</string>
    <string name="class_enrolment">التسجيل في الفصل</string>
    <string name="dropped_out">ترك الدراسة</string>
    <string name="moved">انتقل</string>
    <string name="edit_leaving_reason">تعديل سبب نتيجة التسجيل</string>
    <string name="edit_enrolment">تحرير التسجيل</string>
    <string name="select_leaving_reason">حدد سبب المغادرة</string>
    <string name="add_leaving_reason">أضف سبب مغادرة جديد</string>
    <string name="leaving_reason">ترك السبب</string>
    <string name="leaving_reasons">أسباب ترك</string>
    <string name="class_enrolment_leaving">سبب التسجيل في الفصل للمغادرة</string>
    <string name="outcome">حصيلة</string>
    <string name="enrolment">التسجيل</string>
    <string name="error_start_date_before_previous_enrolment_date">يجب أن يكون التسجيل الجديد بعد نهاية آخر تسجيل لهذا الشخص %1$s</string>
    <string name="time_present">الحالي</string>
    <string name="percentage_score" formatted="false">النتيجة %1$s%%</string>
    <string name="active_classes">فصول نشطة</string>
    <string name="terms_and_policies">الشروط والسياسات</string>
    <string name="manage_site_settings">إدارة إعدادات وسياسات الموقع</string>
    <string name="registration_allowed">يسمح التسجيل</string>
    <string name="edit_site">تحرير الموقع</string>
    <string name="site">موقع</string>
    <string name="powered_by">مشغل بواسطة</string>
    <string name="invalid_email">يرجى إدخال البريد الإلكتروني الصحيح</string>
    <string name="select_account">حدد حساب</string>
    <string name="opening_link">رابط الفتح: %1$s</string>
    <string name="join_class">انضم إلى الفصل</string>
    <string name="edit_filters">تحرير عوامل التصفية</string>
    <string name="field_person_gender">جنس الشخص</string>
    <string name="field_person_age">عمر الشخص</string>
    <string name="connectivity">الاتصال</string>
    <string name="uploading">تحميل</string>
    <string name="confirm_delete_message">هل أنت متأكد أنك تريد حذف هذا الإدخال من جهازك؟</string>
    <string name="processing">معالجة</string>
    <string name="add_a_new_occurrence">أضف حدثًا جديدًا</string>
    <string name="no">لا</string>
    <string name="yes">نعم</string>
    <string name="add_new_language">أضف لغة جديدة</string>
    <string name="languages">اللغات</string>
    <string name="edit_language">تحرير اللغة</string>
    <string name="three_letter_code">رمز من ثلاثة أحرف (ISO 639–2)</string>
    <string name="languages_description">إضافة وإزالة وتعديل اللغات المستخدمة لتصنيف المحتوى التعليمي وتفضيلات المستخدم</string>
    <string name="save_as_template">حفظ كقالب</string>
    <string name="incomplete">غير مكتمل</string>
    <string name="move">يتحرك</string>
    <string name="hide">يخفي</string>
    <string name="attempts">محاولات</string>
    <string name="action_hidden">مختفي</string>
    <string name="average_usage_time_per_user">استخدام المحتوى - متوسط وقت الاستخدام لكل مستخدم</string>
    <string name="number_students_completed">استخدام المحتوى - عدد الطلاب الذين أكملوا المحتوى</string>
    <string name="total_absences">الحضور - الغياب التام</string>
    <string name="percent_students_attended_or_late">الحضور - النسبة المئوية للطلاب الذين حضروا أو تأخروا</string>
    <string name="last_week_date_range">الاسبوع الماضى</string>
    <string name="last_two_week_date_range">الاسبوعين الماضيين</string>
    <string name="two_letter_code">رمز من حرفين (ISO 639–1)</string>
    <string name="and">و</string>
    <string name="added">مضاف</string>
    <string name="add_file_description">أضف محتوى تعليميًا باستخدام التنسيقات المدعومة مثل PDF و xAPI و H5P و EPUB</string>
    <string name="count_session">استخدام المحتوى - عدد الجلسات</string>
    <string name="percent_students_completed">استخدام المحتوى - النسبة المئوية للطلاب الذين أكملوا المحتوى</string>
    <string name="total_attendances">الحضور - إجمالي الحضور</string>
    <string name="total_lates">الحضور - إجمالي فترات التأخير</string>
    <string name="percent_students_attended">الحضور - نسبة الطلاب الذين حضروا</string>
    <string name="total_number_of_classes">الحضور - إجمالي عدد الفصول</string>
    <string name="number_unique_students_attending">الحضور - عدد الطلاب المتفردون الذين يحضرون</string>
    <string name="selected_custom_range">النطاق المخصص: %1$s٪</string>
    <string name="time_range">النطاق الزمني</string>
    <string name="condition_is_not">ليس</string>
    <string name="condition_between">ما بين</string>
    <string name="new_leaving_reason">سبب نتيجة التسجيل الجديد</string>
    <string name="new_enrolment">تسجيل جديد</string>
    <string name="leaving_reason_manage">قم بإضافة وإزالة وتعديل أسباب المغادرة المستخدمة عندما يغادر الطالب الفصل</string>
    <string name="view_profile">عرض الصفحة الشخصية</string>
    <string name="class_enrolment_outcome">نتيجة التسجيل في الفصل</string>
    <string name="person_enrolment_in_class">%1$s تسجيل في %2$s</string>
    <string name="error_start_date_before_clazz_date">لا يمكن أن يبدأ التسجيل قبل تاريخ بدء الفصل</string>
    <string name="guest_login_enabled">تم تفعيل تسجيل دخول الضيف</string>
    <string name="you_are_already_in_school">خطأ: أنت مسجل بالفعل في المدرسة: %1$s</string>
    <string name="what_is_your_date_of_birth">ما هو تاريخ ميلادك؟</string>
    <string name="parents_email_address">البريد الالكتروني للوالدين</string>
    <string name="parent_child_register_message">الوالد العزيز ، طفلك ( %1$s) طلب التسجيل في %2$s . يُرجى الموافقة على الطلب أو رفضه باستخدام الرابط أدناه.%3$s إذا لم يتم قبول الطلب في غضون 30 يومًا ، فسيتم حذف الطلب (وأي معلومات شخصية). يمكنك إبطال الموافقة في أي وقت باستخدام نفس الرابط. شكرًا لك يا %2$s</string>
    <string name="relationship">صلة</string>
    <string name="status_consent_granted">الحالة: تم منح الموافقة (%1$s)</string>
    <string name="view_class_learning_records">عرض سجلات تعلم الفصل</string>
    <string name="edit_socioeconomic_details_of_members">تحرير التفاصيل الاجتماعية والاقتصادية للأعضاء</string>
    <string name="lets_get_started">هيا بنا نبدأ</string>
    <string name="start_from_scratch">بدء من لا شيء</string>
    <string name="add_using_link">أضف باستخدام الارتباط</string>
    <string name="add_using_a_web_link_then">أضف محتوى تعليميًا باستخدام رابط ويب ، ثم استخدمه في وضع عدم الاتصال</string>
    <string name="add_from_gallery">أضف من المعرض</string>
    <string name="current_status_consent_granted">الحالة الحالية: تم منح الموافقة %1$s</string>
    <string name="select_country">حدد الدولة</string>
    <string name="nearby_share">مشاركة قريبة</string>
    <string name="swipe_to_next">مرر سريعًا إلى التالي</string>
    <string name="content_entries_completed">اكتملت إدخالات المحتوى</string>
    <string name="add_educational_content_to_new_learning_env">أضف محتوى تعليميًا (كتبًا إلكترونية ومقاطع فيديو وتمارين تفاعلية والمزيد) خاص بك ، أو قم باستيراده من مواقع ويب أخرى باستخدام رابط. إعداد المدارس والفصول والمجموعات. ثم قم بدعوة الطلاب والمعلمين والموظفين للوصول إليها: عبر الإنترنت أو في وضع عدم الاتصال.</string>
    <string name="use_the_public_lib_env">استخدام بيئة التعلم في المكتبة العامة</string>
    <string name="just_want_to_browse">هل تريد فقط تصفح المحتوى التعليمي واستخدامه في وضع عدم الاتصال دون إدارة المدارس والفصول الدراسية؟ لا مشكلة! تحتوي مكتبتنا العامة على أكثر من 100000 من الموارد التعليمية المفتوحة (OERs) الجاهزة للاستخدام في وضع عدم الاتصال.</string>
    <string name="see_supported_sites">انظر المواقع المدعومة</string>
    <string name="add_remove_and_modify_grades">إضافة وإزالة وتعديل الدرجات مثل رياض الأطفال والصف الأول وما إلى ذلك.</string>
    <string name="add_from_contacts">إضافة من جهات الاتصال</string>
    <string name="sorry_something_went_wrong">عذرا، هناك خطأ ما! لقد سجلناه ، وسنحاول إصلاحه. يرجى التأكد من مشاركة معرف الحادث إذا كنت بحاجة إلى الاتصال بمسؤول النظام حول هذا الأمر.</string>
    <string name="view_basic_profile_of_members">عرض الملف الشخصي الأساسي للأعضاء</string>
    <string name="add_new_clazz_to_school">أضف صفًا جديدًا إلى المدرسة</string>
    <plurals name="number_of_attempts">
        <item quantity="zero">%d محاولات</item>
        <item quantity="one">%d محاولة</item>
        <item quantity="two">%d محاولات</item>
        <item quantity="few">%d محاولات</item>
        <item quantity="many">%d محاولات</item>
        <item quantity="other">%d محاولات</item>
    </plurals>
    <plurals name="duration_minutes">
        <item quantity="zero">%d دقائق</item>
        <item quantity="one">%d دقيقة</item>
        <item quantity="two">%d دقائق</item>
        <item quantity="few">%d دقائق</item>
        <item quantity="many">%d دقائق</item>
        <item quantity="other">%d دقائق</item>
    </plurals>
    <plurals name="duration_seconds">
        <item quantity="zero">%d ثواني</item>
        <item quantity="one">%d ثانية</item>
        <item quantity="two">%d ثواني</item>
        <item quantity="few">%d ثواني</item>
        <item quantity="many">%d ثواني</item>
        <item quantity="other">%d ثواني</item>
    </plurals>
    <plurals name="duration_hours">
        <item quantity="zero">%d ساعات</item>
        <item quantity="one">%d ساعة</item>
        <item quantity="two">%d ساعات</item>
        <item quantity="few">%d ساعات</item>
        <item quantity="many">%d ساعات</item>
        <item quantity="other">%d ساعات</item>
    </plurals>
    <string name="waiting_for_connection">في انتظار الاتصال</string>
    <string name="onboarding_stay_organized_headline">إبقى مرتب</string>
    <string name="edit_assignment">تعديل المهمة</string>
    <string name="mark_penalty">علامة جزاء</string>
    <string name="late_submission_penalty">غرامة التقديم المتأخر</string>
    <string name="end_of_grace_period">نهاية فترة السماح</string>
    <string name="after_deadline_date_error">يجب أن يكون بعد تاريخ الموعد النهائي</string>
    <string name="points">نقاط</string>
    <string name="minimum_score">الحد الأدنى من النقاط</string>
    <string name="automatic">تلقائي</string>
    <string name="student_marks_content">يصنف الطلبة انفسهم</string>
    <string name="mark_complete">وضع علامة كاملة</string>
    <string name="connect">الاتصال</string>
    <string name="downloading_content">تنزيل %1$s</string>
    <string name="deleting_content">حذف %1$s</string>
    <string name="add_folder_description">أضف كافة محتويات التعليم المدعومة من مجلد</string>
    <string name="upload">تحميل</string>
    <string name="saved">تم حفظه</string>
    <string name="individual">فرد</string>
    <string name="dont_show_before">لا تظهر من قبل</string>
    <string name="require_file_submission">تتطلب تقديم الملف</string>
    <string name="require_text_submission">طلب تقديم النص</string>
    <string name="maximum">أقصى</string>
    <string name="size_limit">حد الحجم (ميغا بايت)</string>
    <string name="limit">حد</string>
    <string name="number_of_files">أقصى عدد من الملفات</string>
    <string name="edit_after_submission">التحرير بعد التقديم</string>
    <string name="allowed_till_grace">مسموح به حتى نهاية فترة السماح</string>
    <string name="not_allowed">غير مسموح</string>
    <string name="marked_by">علمت بواسطة</string>
    <string name="peers">الأقران</string>
    <string name="file_type">نوع الملف</string>
    <string name="file_type_chosen">يكتب</string>
    <string name="file_document">المستند (pdf، docx، odt)</string>
    <string name="file_image">صورة</string>
    <string name="max_number_of_files">أقصى عدد من الملفات: %1$s</string>
    <string name="submit_grade">إرسال الدرجة</string>
    <string name="graded">منقط</string>
    <string name="score_greater_than_zero">يجب أن يكون أكبر من 0</string>
    <string name="words">كلمات</string>
    <string name="characters">الشخصيات</string>
    <string name="maximum_points">الحد الأقصى من النقاط</string>
    <string name="submissions">التقديمات</string>
    <string name="add_text">أضف نصًا</string>
    <string name="course_blocks">كتل الدورة</string>
    <string name="edit_block">تحرير الكتلة</string>
    <string name="module">وحدة</string>
    <string name="course_module">وحدة الدورة</string>
    <string name="formatted_text_to_show_to_course_participants">الكتلة التي ستعرض النص المنسق</string>
    <string name="add_course_block_content_desc">أضف صوتًا أو فيديو أو كتبًا إلكترونية أو محتوى تفاعليًا (H5P ، xAPI ، إلخ) من الملفات أو الروابط</string>
    <string name="add_assignment_block_content_desc">مهمة لإكمال المشاركين في الدورة</string>
    <string name="discussion_board">لوحة النقاش</string>
    <string name="new_module">وحدة جديدة</string>
    <string name="edit_module">تحرير وحدة</string>
    <string name="indent">مسافة بادئة</string>
    <string name="institution">مؤسسة</string>
    <string name="open_enrolment">فتح التسجيل</string>
    <string name="enrolment_requests_must_be_approved">يجب الموافقة على طلبات التسجيل</string>
    <string name="visibility">الرؤية</string>
    <string name="terminology">المصطلح</string>
    <string name="edit_terminology">تحرير المصطلحات</string>
    <string name="your_words_for">كلماتك ل</string>
    <string name="course_setup">إعداد الدورة</string>
    <string name="number_of_groups">عدد المجموعات</string>
    <string name="assign_to_random_groups">خصص لمجموعات عشوائية</string>
    <string name="add_new_groups">أضف مجموعات جديدة</string>
    <string name="library">مكتبة</string>
    <string name="courses">الدورات</string>
    <string name="course">مسار</string>
    <string name="reports_and_analytics">التقارير والتحليلات</string>
    <string name="currently_enroled">مسجل حاليًا</string>
    <string name="past_enrolments">التسجيلات السابقة</string>
    <string name="group_number" formatted="false">المجموعة %1$s</string>
    <string name="clazz_assignment">مهمة</string>
    <string name="late_submission">عمليات الإرسال المتأخرة</string>
    <string name="allow_class_comments">السماح بتعليقات الفصل من الطلاب</string>
    <string name="completion_criteria">معايير الإنجاز</string>
    <string name="late_penalty">(%1$s%% غرامة متأخرة)</string>
    <string name="add_folder">أضف الكل من المجلد</string>
    <string name="importing">استيراد %1$s</string>
    <string name="parent">الأبوين</string>
    <string name="selected_file_summary">تم تحديد %1$s (%2$s)</string>
    <string name="group">مجموعة</string>
    <string name="allowed_till_deadline">مسموح حتى الموعد النهائي</string>
    <string name="submit_grade_and_mark_next">إرسال الدرجة ووضع علامة بعد ذلك</string>
    <string name="penalty_label">إذا اكتمل بعد الموعد النهائي ولكن قبل نهاية فترة السماح</string>
    <string name="add_block">إضافة كتلة</string>
    <string name="add_discussion_board_desc">مناقشة منظمة مع المواضيع والمواضيع</string>
    <string name="select_terminology">حدد المصطلحات</string>
    <string name="add_new_terminology">أضف مصطلحات جديدة</string>
    <string name="course_code">كود الدورة</string>
    <string name="blank_report">تقرير فارغ</string>
    <string name="onboarding_stay_organized_subheading">محتوى التعليم والواجبات والفصول الدراسية والحضور كلها في مكان واحد</string>
    <string name="your_account_needs_approved">يجب أن يوافق والديك على حسابك باستخدام الرابط الذي تم إرساله. إذا كنت أحد الوالدين ، فأنت بحاجة إلى تسجيل الدخول إلى حسابك الحالي أو إنشاء حساب جديد.</string>
    <string name="percentage_of_students_attending_over_time">النسبة المئوية للطلاب الذين يحضرون بمرور الوقت</string>
    <string name="content_completion">إكمال المحتوى</string>
    <string name="number_of_students_completed_time">عدد الطلاب الذين أكملوا المحتوى المحدد</string>
    <string name="content_usage_by_class">استخدام المحتوى حسب الفصل</string>
    <string name="total_content_usage_duration_class">إجمالي مدة استخدام المحتوى مجموعة فرعية حسب الفئة</string>
    <string name="content_usage_over_time">استخدام المحتوى بمرور الوقت</string>
    <string name="total_content_duration_gender">إجمالي مدة استخدام المحتوى بمرور الوقت (مصنفة حسب الجنس)</string>
    <string name="unique_content_users_over_time">مستخدمو المحتوى الفريد بمرور الوقت</string>
    <string name="number_of_active_users_over_time">عدد المستخدمين النشطين بمرور الوقت</string>
    <string name="drag_and_drop_or_click_to_add_file">قم بسحب وإسقاط ملف هنا أو انقر</string>
    <string name="extra_active_tab_warning">نحن لا ندعم عدة علامات تبويب تعمل في نفس الوقت ، أغلق علامة التبويب هذه.</string>
    <string name="file_type_any">أي</string>
    <string name="class_timezone_set">المنطقة الزمنية للفصل الدراسي: %1$s</string>
    <string name="unindent">Unindent</string>
    <string name="student_enrolment_policy">سياسة تسجيل الطلاب</string>
    <string name="teacher_enrolment_policy">سياسة التحاق المعلم</string>
    <string name="accept_enrolment_requests_automatically">قبول طلبات التسجيل تلقائيًا</string>
    <string name="hidden_enrolment_via_links_code_or_invitation">مخفي (التسجيل عبر الروابط أو الكود أو الدعوة)</string>
    <string name="visible_for_all">مرئي للجميع</string>
    <string name="num_replies">%1$d ردود</string>
    <string name="topics">المواضيع</string>
    <string name="add_topic">أضف الموضوع</string>
    <string name="add_a_reply">أضف ردًا</string>
    <string name="messages">رسائل</string>
    <string name="message">رسالة</string>
    <string name="course_comments">تعليقات الدورة</string>
    <string name="standard">اساسي</string>
    <string name="edit_group">تحرير المجموعة</string>
    <string name="new_group_set">مجموعة مجموعة جديدة</string>
    <string name="edit_text">تحرير النص</string>
    <string name="add_module">إضافة وحدة</string>
    <string name="add_a_new_course">أضف دورة جديدة</string>
    <string name="join_existing_course">انضم إلى الدورة الحالية</string>
    <string name="edit_course">تحرير الدورة</string>
    <string name="currently_enrolled">المسجلين حاليا</string>
    <string name="past_enrollments">التسجيلات السابقة</string>
    <string name="individual_submission">تقديم فردي</string>
    <string name="edit_topic">تحرير الموضوع</string>
    <string name="parent_consent_explanation">أؤكد أنني أحد الوالدين أو الوصي القانوني للطفل التالي:&#13;
\n&#13;
\n الاسم: %1$s&#13;
\n تاريخ الميلاد: %2$s &#13;
\nإذا وافقت على استخدام طفلي لـ %3$s ، فسيتم جمع ومعالجة معلومات التعريف سيتم إجراء المعلومات وفقًا لسياسة الخصوصية والشروط والأحكام الواردة أدناه. يمكن إبطال الموافقة في أي وقت باستخدام الرابط الذي تم إرساله عبر البريد الإلكتروني. إذا اخترت عدم الموافقة ، فسيتم حذف أي بيانات يقدمها طفلك في غضون 24 ساعة.</string>
    <string name="adult_account_required">مطلوب حساب الكبار لفتح هذا الرابط. إذا كنت أحد الوالدين ، فأنت بحاجة إلى تسجيل الدخول إلى حسابك الحالي أو إنشاء حساب جديد.</string>
    <string name="attendance_over_time_by_class">الحضور بمرور الوقت حسب الفصل</string>
    <string name="unread">غير مقروء</string>
    <string name="new_chat">محادثة جديدة</string>
    <string name="chat">محادثة</string>
    <string name="you">أنت</string>
    <string name="posts">المشاركات</string>
    <string name="post">بريد</string>
    <string name="unassigned">غير معين</string>
    <string name="error_too_long_text">نص طويل جدًا</string>
    <string name="managed_enrolment">مُدار - يجب دعوته أو الموافقة عليه</string>
    <string name="text_file_submission_error">يجب استخدام النص و/أو تقديم الملف</string>
    <string name="submit_all_at_once_submission_policy">يجب أن يقدم كل دفعة واحدة</string>
    <string name="multiple_submission_allowed_submission_policy">يمكن إجراء عمليات إرسال متعددة</string>
    <string name="enrolment_policy">سياسة التسجيل</string>
    <string name="submission_policy">سياسة التقديم</string>
    <string name="submission_already_made">تم التقديم بالفعل</string>
    <string name="grade_out_of_range">يجب أن تكون الدرجة بين 0 و %1$s</string>
    <string name="update_grade">تحديث الدرجة</string>
    <string name="update_grade_and_mark_next">تحديث الدرجة ووضع علامة المقبل</string>
    <string name="add_discussion">أضف مناقشة</string>
    <string name="edit_discussion">تحرير المناقشة</string>
</resources>